github_commits_fetcher/__init__.py
github_commits_fetcher/fetcher.py
github_commits_fetcher-0.1.1.dist-info/LICENSE
github_commits_fetcher-0.1.1.dist-info/METADATA
github_commits_fetcher-0.1.1.dist-info/WHEEL
github_commits_fetcher-0.1.1.dist-info/entry_points.txt
github_commits_fetcher-0.1.1.dist-info/top_level.txt
github_commits_fetcher-0.1.1.dist-info/RECORD
