Metadata-Version: 2.1
Name: github_commits_fetcher
Version: 0.1.1
Summary: A tool to fetch and process GitHub commits
Home-page: https://github.com/chenxingqiang/github_commits_fetcher
Author: xingqiang chen
Author-email: joy6677@qq.com
Classifier: Programming Language :: Python :: 3
Classifier: License :: OSI Approved :: MIT License
Classifier: Operating System :: OS Independent
Requires-Python: >=3.6
License-File: LICENSE
Requires-Dist: requests
Requires-Dist: pandas
Requires-Dist: python-dotenv
